opencc_purepy/__init__.py
opencc_purepy/__main__.py
opencc_purepy/convert_cmd.py
opencc_purepy/core.py
opencc_purepy/dictgen_cmd.py
opencc_purepy/dictionary_lib.py
opencc_purepy/office_cmd.py
opencc_purepy/office_helper.py
opencc_purepy/dicts/HKVariants.txt
opencc_purepy/dicts/HKVariantsRev.txt
opencc_purepy/dicts/HKVariantsRevPhrases.txt
opencc_purepy/dicts/JPShinjitaiCharacters.txt
opencc_purepy/dicts/JPShinjitaiPhrases.txt
opencc_purepy/dicts/JPVariants.txt
opencc_purepy/dicts/JPVariantsRev.txt
opencc_purepy/dicts/STCharacters.txt
opencc_purepy/dicts/STPhrases.txt
opencc_purepy/dicts/TSCharacters.txt
opencc_purepy/dicts/TSPhrases.txt
opencc_purepy/dicts/TWPhrases.txt
opencc_purepy/dicts/TWPhrasesRev.txt
opencc_purepy/dicts/TWVariants.txt
opencc_purepy/dicts/TWVariantsRev.txt
opencc_purepy/dicts/TWVariantsRevPhrases.txt
opencc_purepy/dicts/dictionary_maxlength.json
opencc_purepy-1.1.0.dist-info/licenses/LICENSE
opencc_purepy-1.1.0.dist-info/METADATA
opencc_purepy-1.1.0.dist-info/WHEEL
opencc_purepy-1.1.0.dist-info/entry_points.txt
opencc_purepy-1.1.0.dist-info/top_level.txt
opencc_purepy-1.1.0.dist-info/RECORD
