Metadata-Version: 2.4
Name: opencc-purepy
Version: 1.1.0
Summary: Pure Python implementation of OpenCC for Chinese text conversion
Author-email: laisuk <laisuk@yahoo.com>
License: MIT
Project-URL: Homepage, https://github.com/laisuk/opencc_purepy
Project-URL: Issues, https://github.com/laisuk/opencc_purepy/issues
Project-URL: ChangeLog, https://github.com/laisuk/opencc_purepy/blob/master/CHANGELOG.md
Keywords: opencc,chinese,text,conversion,pure-python
Classifier: Programming Language :: Python :: 3
Classifier: Programming Language :: Python :: 3.7
Classifier: Programming Language :: Python :: 3.8
Classifier: Programming Language :: Python :: 3.9
Classifier: Programming Language :: Python :: 3.10
Classifier: Programming Language :: Python :: 3.11
Classifier: Programming Language :: Python :: 3.12
Classifier: Programming Language :: Python :: 3.13
Classifier: Programming Language :: Python :: 3.14
Classifier: License :: OSI Approved :: MIT License
Classifier: Operating System :: OS Independent
Classifier: Topic :: Text Processing :: Linguistic
Classifier: Environment :: Console
Classifier: Intended Audience :: Developers
Requires-Python: >=3.7
License-File: LICENSE
Dynamic: license-file
